rwandaphoneformat/__init__.py
rwandaphoneformat/format_phone.py
rwandaphoneformat-0.1.11.dist-info/METADATA
rwandaphoneformat-0.1.11.dist-info/WHEEL
rwandaphoneformat-0.1.11.dist-info/RECORD
