Metadata-Version: 2.1
Name: rwandaphoneformat
Version: 0.1.11
Summary: 
Author: Jean Eric TUYISHIMIRE
Author-email: ericjohn415@gmail.com
Requires-Python: >=3.8,<4.0
Classifier: Programming Language :: Python :: 3
Classifier: Programming Language :: Python :: 3.8
Classifier: Programming Language :: Python :: 3.9
Classifier: Programming Language :: Python :: 3.10
Classifier: Programming Language :: Python :: 3.11
